tlvisuals/__init__.py
tlvisuals/__main__.py
tlvisuals/tlv.py
tlvisuals/tlv_parser.py
tlvisuals/output_builder/__init__.py
tlvisuals/output_builder/raw_format.py
tlvisuals-0.0.5.dist-info/LICENSE
tlvisuals-0.0.5.dist-info/METADATA
tlvisuals-0.0.5.dist-info/WHEEL
tlvisuals-0.0.5.dist-info/top_level.txt
tlvisuals-0.0.5.dist-info/RECORD
